curies/__init__.py
curies/__main__.py
curies/api.py
curies/cli.py
curies/database.py
curies/dataframe.py
curies/discovery.py
curies/mixins.py
curies/preprocessing.py
curies/py.typed
curies/reconciliation.py
curies/resolver_service.py
curies/sources.py
curies/triples.py
curies/utils.py
curies/version.py
curies/vocabulary.py
curies/w3c.py
curies/mapping_service/__init__.py
curies/mapping_service/api.py
curies/mapping_service/rdflib_custom.py
curies/mapping_service/utils.py
curies-0.12.8.dist-info/METADATA
curies-0.12.8.dist-info/WHEEL
curies-0.12.8.dist-info/entry_points.txt
curies-0.12.8.dist-info/licenses/LICENSE
curies-0.12.8.dist-info/RECORD
