Metadata-Version: 2.4
Name: curies
Version: 0.12.8
Summary: Idiomatic conversion between URIs and compact URIs (CURIEs)
Project-URL: Bug Tracker, https://github.com/biopragmatics/curies/issues
Project-URL: Homepage, https://github.com/biopragmatics/curies
Project-URL: Repository, https://github.com/biopragmatics/curies.git
Project-URL: Documentation, https://curies.readthedocs.io
Project-URL: Funding, https://github.com/sponsors/cthoyt
Author-email: Charles Tapley Hoyt <cthoyt@gmail.com>
Maintainer-email: Charles Tapley Hoyt <cthoyt@gmail.com>
License-File: LICENSE
Keywords: IRIs,URIs,compact uniform resource identifiers,cookiecutter,curies,semantic web,snekpack,uniform resource identifiers
Classifier: Development Status :: 5 - Production/Stable
Classifier: Environment :: Console
Classifier: Framework :: Pytest
Classifier: Framework :: Sphinx
Classifier: Framework :: tox
Classifier: Intended Audience :: Developers
Classifier: License :: OSI Approved :: MIT License
Classifier: Natural Language :: English
Classifier: Operating System :: OS Independent
Classifier: Programming Language :: Python
Classifier: Programming Language :: Python :: 3 :: Only
Classifier: Programming Language :: Python :: 3.10
Classifier: Programming Language :: Python :: 3.11
Classifier: Programming Language :: Python :: 3.12
Classifier: Programming Language :: Python :: 3.13
Classifier: Typing :: Typed
Requires-Python: >=3.10
Requires-Dist: pydantic>=2.0
Requires-Dist: typing-extensions
Provides-Extra: docs
Requires-Dist: sphinx-automodapi; extra == 'docs'
Requires-Dist: sphinx-rtd-theme>=3.0; extra == 'docs'
Requires-Dist: sphinx>=8; extra == 'docs'
Provides-Extra: fastapi
Requires-Dist: defusedxml; extra == 'fastapi'
Requires-Dist: fastapi; extra == 'fastapi'
Requires-Dist: httpx; extra == 'fastapi'
Requires-Dist: python-multipart; extra == 'fastapi'
Requires-Dist: uvicorn; extra == 'fastapi'
Provides-Extra: flask
Requires-Dist: defusedxml; extra == 'flask'
Requires-Dist: flask; extra == 'flask'
Provides-Extra: pandas
Requires-Dist: pandas; extra == 'pandas'
Provides-Extra: rdflib
Requires-Dist: rdflib; extra == 'rdflib'
Provides-Extra: sqlalchemy
Requires-Dist: sqlalchemy; extra == 'sqlalchemy'
Provides-Extra: sqlmodel
Requires-Dist: sqlmodel; extra == 'sqlmodel'
Provides-Extra: tests
Requires-Dist: coverage[toml]; extra == 'tests'
Requires-Dist: pytest; extra == 'tests'
Requires-Dist: requests; extra == 'tests'
